{
  "Name": "Azure.Messaging.WebPubSub.Client",
  "Version": "1.0.0",
  "DevVersion": null,
  "DirectoryPath": "sdk/webpubsub/Azure.Messaging.WebPubSub.Client",
  "ServiceDirectory": "webpubsub",
  "ReadMePath": "sdk/webpubsub/Azure.Messaging.WebPubSub.Client/README.md",
  "ChangeLogPath": "sdk/webpubsub/Azure.Messaging.WebPubSub.Client/CHANGELOG.md",
  "Group": null,
  "SdkType": "client",
  "IsNewSdk": true,
  "ArtifactName": "Azure.Messaging.WebPubSub.Client",
  "ReleaseStatus": "2023-12-01",
  "Namespaces": [
    "Azure.Messaging.WebPubSub.Clients"
  ]
}
