{
  "Name": "Azure.ResourceManager.Chaos",
  "Version": "1.0.0",
  "DevVersion": null,
  "DirectoryPath": "sdk/chaos/Azure.ResourceManager.Chaos",
  "ServiceDirectory": "chaos",
  "ReadMePath": "sdk/chaos/Azure.ResourceManager.Chaos/README.md",
  "ChangeLogPath": "sdk/chaos/Azure.ResourceManager.Chaos/CHANGELOG.md",
  "Group": null,
  "SdkType": "mgmt",
  "IsNewSdk": true,
  "ArtifactName": "Azure.ResourceManager.Chaos",
  "ReleaseStatus": "2024-01-17",
  "Namespaces": [
    "Azure.ResourceManager.Chaos",
    "Azure.ResourceManager.Chaos.Mocking",
    "Azure.ResourceManager.Chaos.Models"
  ]
}
