{
  "Name": "Azure.ResourceManager.Billing",
  "Version": "1.1.0",
  "DevVersion": null,
  "DirectoryPath": "sdk/billing/Azure.ResourceManager.Billing",
  "ServiceDirectory": "billing",
  "ReadMePath": "sdk/billing/Azure.ResourceManager.Billing/README.md",
  "ChangeLogPath": "sdk/billing/Azure.ResourceManager.Billing/CHANGELOG.md",
  "Group": null,
  "SdkType": "mgmt",
  "IsNewSdk": true,
  "ArtifactName": "Azure.ResourceManager.Billing",
  "ReleaseStatus": "2023-11-27",
  "Namespaces": [
    "Azure.ResourceManager.Billing",
    "Azure.ResourceManager.Billing.Mocking",
    "Azure.ResourceManager.Billing.Models"
  ],
  "DocsCiConfigProperties": {
    "tfm": "netstandard2.0"
  },
  "MSDocService": "placeholder"
}
