{
  "Name": "Azure.ResourceManager",
  "Version": "1.10.1",
  "DevVersion": null,
  "DirectoryPath": "sdk/resourcemanager/Azure.ResourceManager",
  "ServiceDirectory": "resourcemanager",
  "ReadMePath": "sdk/resourcemanager/Azure.ResourceManager/README.md",
  "ChangeLogPath": "sdk/resourcemanager/Azure.ResourceManager/CHANGELOG.md",
  "Group": null,
  "SdkType": "mgmt",
  "IsNewSdk": true,
  "ArtifactName": "Azure.ResourceManager",
  "ReleaseStatus": "2024-01-26",
  "Namespaces": [
    "Azure.ResourceManager",
    "Azure.ResourceManager.ManagementGroups",
    "Azure.ResourceManager.ManagementGroups.Models",
    "Azure.ResourceManager.Models",
    "Azure.ResourceManager.Resources",
    "Azure.ResourceManager.Resources.Models",
    "Microsoft.Extensions.Azure"
  ],
  "DocsCiConfigProperties": {
    "tfm": "netstandard2.0"
  },
  "MSDocService": "placeholder"
}
