{
  "Name": "Azure.ResourceManager.Communication",
  "Version": "1.2.1",
  "DevVersion": null,
  "DirectoryPath": "sdk/communication/Azure.ResourceManager.Communication",
  "ServiceDirectory": "communication",
  "ReadMePath": "sdk/communication/Azure.ResourceManager.Communication/README.md",
  "ChangeLogPath": "sdk/communication/Azure.ResourceManager.Communication/CHANGELOG.md",
  "Group": null,
  "SdkType": "mgmt",
  "IsNewSdk": true,
  "ArtifactName": "Azure.ResourceManager.Communication",
  "ReleaseStatus": "2025-03-11",
  "IncludedForValidation": false,
  "AdditionalValidationPackages": null,
  "ArtifactDetails": {
    "safeName": "AzureResourceManagerCommunication",
    "triggeringPaths": [
      "/sdk/communication/ci.mgmt.yml"
    ],
    "name": "Azure.ResourceManager.Communication"
  },
  "CIParameters": {
    "CIMatrixConfigs": []
  },
  "Namespaces": [
    "Azure.ResourceManager.Communication",
    "Azure.ResourceManager.Communication.Mocking",
    "Azure.ResourceManager.Communication.Models"
  ],
  "DocsCiConfigProperties": {
    "tfm": "netstandard2.0"
  },
  "MSDocService": "placeholder"
}
