{
  "Name": "Azure.Storage.Blobs.ChangeFeed",
  "Version": "12.0.0-alpha.20250508.1",
  "DevVersion": "12.0.0-alpha.20250508.1",
  "DirectoryPath": "sdk/storage/Azure.Storage.Blobs.ChangeFeed",
  "ServiceDirectory": "storage",
  "ReadMePath": "sdk/storage/Azure.Storage.Blobs.ChangeFeed/README.md",
  "ChangeLogPath": "sdk/storage/Azure.Storage.Blobs.ChangeFeed/CHANGELOG.md",
  "Group": null,
  "SdkType": "client",
  "IsNewSdk": true,
  "ArtifactName": "Azure.Storage.Blobs.ChangeFeed",
  "ReleaseStatus": "Unreleased",
  "IncludedForValidation": false,
  "AdditionalValidationPackages": null,
  "ArtifactDetails": {
    "safeName": "AzureStorageBlobsChangeFeed",
    "skipSmokeTests": true,
    "name": "Azure.Storage.Blobs.ChangeFeed",
    "triggeringPaths": [
      "/sdk/storage/ci.yml"
    ]
  },
  "CIParameters": {
    "AOTTestInputs": null,
    "BuildSnippets": false,
    "CheckAOTCompat": true,
    "CIMatrixConfigs": []
  },
  "Namespaces": [
    "Azure.Storage.Blobs.ChangeFeed"
  ],
  "CIMatrixConfigs": [],
  "DocsCiConfigProperties": {
    "isPrerelease": "true",
    "tfm": "netstandard2.0"
  },
  "MSDocService": "placeholder"
}
