{
  "Name": "Azure.Compute.Batch",
  "Version": "1.0.0-beta.1",
  "DevVersion": null,
  "DirectoryPath": "sdk/batch/Azure.Compute.Batch",
  "ServiceDirectory": "batch",
  "ReadMePath": "sdk/batch/Azure.Compute.Batch/README.md",
  "ChangeLogPath": "sdk/batch/Azure.Compute.Batch/CHANGELOG.md",
  "Group": null,
  "SdkType": "client",
  "IsNewSdk": true,
  "ArtifactName": "Azure.Compute.Batch",
  "ReleaseStatus": "2024-06-01",
  "Namespaces": [
    "Azure.Compute.Batch",
    "Microsoft.Extensions.Azure"
  ]
}
