{
  "Name": "Azure.Maps.Geolocation",
  "Version": "1.0.0-alpha.20250505.1",
  "DevVersion": "1.0.0-alpha.20250505.1",
  "DirectoryPath": "sdk/maps/Azure.Maps.Geolocation",
  "ServiceDirectory": "maps",
  "ReadMePath": "sdk/maps/Azure.Maps.Geolocation/README.md",
  "ChangeLogPath": "sdk/maps/Azure.Maps.Geolocation/CHANGELOG.md",
  "Group": null,
  "SdkType": "client",
  "IsNewSdk": true,
  "ArtifactName": "Azure.Maps.Geolocation",
  "ReleaseStatus": "Unreleased",
  "IncludedForValidation": false,
  "AdditionalValidationPackages": null,
  "ArtifactDetails": {
    "name": "Azure.Maps.Geolocation",
    "triggeringPaths": [
      "/sdk/maps/ci.yml"
    ],
    "safeName": "AzureMapsGeolocation"
  },
  "CIParameters": {
    "BuildSnippets": true,
    "AOTTestInputs": [],
    "CheckAOTCompat": false,
    "CIMatrixConfigs": []
  },
  "Namespaces": [
    "Azure.Maps.Geolocation"
  ],
  "CIMatrixConfigs": [],
  "DocsCiConfigProperties": {
    "isPrerelease": "true",
    "tfm": "netstandard2.0"
  },
  "MSDocService": "placeholder"
}
