{
  "Name": "Azure.Provisioning.Resources",
  "Version": "0.2.0-alpha.20240716.1",
  "DevVersion": "0.2.0-alpha.20240716.1",
  "DirectoryPath": "sdk/provisioning/Azure.Provisioning.Resources",
  "ServiceDirectory": "provisioning",
  "ReadMePath": "sdk/provisioning/Azure.Provisioning.Resources/README.md",
  "ChangeLogPath": "sdk/provisioning/Azure.Provisioning.Resources/CHANGELOG.md",
  "Group": null,
  "SdkType": "mgmt",
  "IsNewSdk": true,
  "ArtifactName": "Azure.Provisioning.Resources",
  "ReleaseStatus": "2024-05-14",
  "Namespaces": [
    "Azure.Provisioning.Resources"
  ]
}
