{
  "Name": "Azure.ResourceManager.PolicyInsights",
  "Version": "1.0.0-beta.1",
  "DevVersion": null,
  "DirectoryPath": "sdk/policyinsights/Azure.ResourceManager.PolicyInsights",
  "ServiceDirectory": "policyinsights",
  "ReadMePath": "sdk/policyinsights/Azure.ResourceManager.PolicyInsights/README.md",
  "ChangeLogPath": "sdk/policyinsights/Azure.ResourceManager.PolicyInsights/CHANGELOG.md",
  "Group": null,
  "SdkType": "mgmt",
  "IsNewSdk": true,
  "ArtifactName": "Azure.ResourceManager.PolicyInsights",
  "ReleaseStatus": "2022-08-29"
}
